_plibflac.abi3.so
plibflac/_decoder.py
plibflac/__init__.py
plibflac/_encoder.py
plibflac-0.3.0.dist-info/RECORD
plibflac-0.3.0.dist-info/WHEEL
plibflac-0.3.0.dist-info/top_level.txt
plibflac-0.3.0.dist-info/METADATA
plibflac-0.3.0.dist-info/licenses/LICENSE
