Metadata-Version: 2.4
Name: plibflac
Version: 0.3.0
Summary: Read and write FLAC audio files
Author-email: Benjamin Moody <bmoody@mit.edu>
Classifier: Development Status :: 4 - Beta
Classifier: Intended Audience :: Developers
Classifier: License :: OSI Approved :: GNU General Public License v3 or later (GPLv3+)
Classifier: Programming Language :: Python :: 3
Classifier: Topic :: Multimedia :: Sound/Audio :: Conversion
Requires-Python: >=3.5
License-File: LICENSE
Dynamic: license-file
